[
  {
    "id": 1,
    "customer_name": "Title_1",
    "service_center_id": 1,
    "service_provider_id": 1,
    "slot_id": 1,
    "slot": "08:00",
    "bookingDate": "2024-01-02"
  },
  {
    "id": 2,
    "customer_name": "Title_2",
    "service_center_id": 2,
    "service_provider_id": 1,
    "slot_id": 2,
    "slot": "08:00",
    "bookingDate": "2024-01-05"
  },
  {
    "id": 3,
    "customer_name": "Title_3",
    "service_center_id": 3,
    "service_provider_id": 2,
    "slot_id": 3,
    "slot": "08:00",
    "bookingDate": "2024-01-22"
  }
]
